animeX/__init__.py
animeX/__main__.py
animeX/animeX.py
animeX/utils.py
tests/__init__.py
animeX-0.2.0.dist-info/LICENSE
animeX-0.2.0.dist-info/METADATA
animeX-0.2.0.dist-info/WHEEL
animeX-0.2.0.dist-info/top_level.txt
animeX-0.2.0.dist-info/RECORD
