Metadata-Version: 2.1
Name: animeX
Version: 0.2.0
Summary: A simple, yet versatile package for downloading anime.
Home-page: https://github.com/mastersam07/animeX-pack
Author: Samuel Abada
Author-email: abadasamuelosp@gmail.com
License: UNKNOWN
Project-URL: Bug Reports, https://github.com/Mastersam07/animeX-pack/issues
Project-URL: Read the Docs, https://animex-pack.readthedocs.io/en/latest/
Keywords: anime,download,video
Platform: UNKNOWN
Classifier: Environment :: Console
Classifier: Intended Audience :: Developers
Classifier: Natural Language :: English
Classifier: Programming Language :: Python :: 3
Classifier: Programming Language :: Python :: 3.6
Classifier: Programming Language :: Python :: 3.7
Classifier: Programming Language :: Python :: 3.8
Classifier: Programming Language :: Python
Classifier: License :: OSI Approved :: MIT License
Classifier: Operating System :: OS Independent
Classifier: Topic :: Software Development :: Libraries :: Python Modules
Classifier: Topic :: Utilities
Classifier: Topic :: Internet
Classifier: Topic :: Multimedia :: Video
Requires-Python: >=3.6
Requires-Dist: wget (==3.2)
Requires-Dist: requests (==2.21.0)
Requires-Dist: beautifulsoup4 (==4.9.0)
